LICENSE
MANIFEST.in
README.rst
setup.py
main/__init__.py
main/asgi.py
main/routing.py
main/settings.py
main/urls.py
main/wsgi.py
spreadsheetui/__init__.py
spreadsheetui/admin.py
spreadsheetui/apps.py
spreadsheetui/exceptions.py
spreadsheetui/models.py
spreadsheetui/tasks.py
spreadsheetui/tests.py
spreadsheetui/urls.py
spreadsheetui/views.py
spreadsheetui.egg-info/PKG-INFO
spreadsheetui.egg-info/SOURCES.txt
spreadsheetui.egg-info/dependency_links.txt
spreadsheetui.egg-info/requires.txt
spreadsheetui.egg-info/top_level.txt
spreadsheetui/migrations/0001_initial.py
spreadsheetui/migrations/0002_auto_20200522_0752.py
spreadsheetui/migrations/0003_auto_20200522_1102.py
spreadsheetui/migrations/0004_job_blocking_job.py
spreadsheetui/migrations/0005_auto_20200607_0957.py
spreadsheetui/migrations/0006_auto_20220527_0745.py
spreadsheetui/migrations/__init__.py
spreadsheetui/static/spreadsheetui/3rdpartylicenses.txt
spreadsheetui/static/spreadsheetui/favicon.ico
spreadsheetui/static/spreadsheetui/index.html
spreadsheetui/static/spreadsheetui/main.a86c1ad50c69eba5.js
spreadsheetui/static/spreadsheetui/polyfills.8068f69ffe87d51f.js
spreadsheetui/static/spreadsheetui/runtime.112d33be89d69065.js
spreadsheetui/static/spreadsheetui/styles.cb6fcd27277ddaea.css
spreadsheetui/static/spreadsheetui/assets/icons/android-icon-144x144.png
spreadsheetui/static/spreadsheetui/assets/icons/android-icon-192x192.png
spreadsheetui/static/spreadsheetui/assets/icons/android-icon-36x36.png
spreadsheetui/static/spreadsheetui/assets/icons/android-icon-48x48.png
spreadsheetui/static/spreadsheetui/assets/icons/android-icon-72x72.png
spreadsheetui/static/spreadsheetui/assets/icons/android-icon-96x96.png
spreadsheetui/static/spreadsheetui/assets/icons/apple-icon-114x114.png
spreadsheetui/static/spreadsheetui/assets/icons/apple-icon-120x120.png
spreadsheetui/static/spreadsheetui/assets/icons/apple-icon-144x144.png
spreadsheetui/static/spreadsheetui/assets/icons/apple-icon-152x152.png
spreadsheetui/static/spreadsheetui/assets/icons/apple-icon-180x180.png
spreadsheetui/static/spreadsheetui/assets/icons/apple-icon-57x57.png
