Metadata-Version: 2.1
Name: spreadsheetui
Version: 1.2.0
Summary: Multiclient bittorrent webui
Home-page: https://github.com/JohnDoee/spreadsheetui
Author: Anders Jensen
Author-email: jd@tridentstream.org
License: MIT
Classifier: Development Status :: 3 - Alpha
Classifier: Environment :: Web Environment
Classifier: Framework :: Twisted
Classifier: Intended Audience :: End Users/Desktop
Classifier: License :: OSI Approved :: MIT License
Classifier: Operating System :: OS Independent
Classifier: Programming Language :: Python
Classifier: Programming Language :: Python :: 3.6
Classifier: Programming Language :: Python :: 3.7
Classifier: Topic :: Internet :: WWW/HTTP
License-File: LICENSE
